<?xml version="1.0" encoding="utf-8" standalone="yes"?>
<imgdir name="01102257.img">
    <imgdir name="info">
        <canvas name="icon" width="30" height="33">
            <vector name="origin" x="-2" y="32" />
            <string name="_hash" value="4d79d247823909fe97d8aa07710eaec6841b208c65a9e6c7760b5807f1361533" />
        </canvas>
        <canvas name="iconRaw" width="30" height="32">
            <vector name="origin" x="-1" y="32" />
            <string name="_hash" value="8f4fd5701de57fdfc5823f94662a420f5b70755c31a392cbeebf38e8bddf521b" />
        </canvas>
        <string name="islot" value="Sr" />
        <string name="vslot" value="Sr" />
        <int name="reqJob" value="0" />
        <int name="reqLevel" value="0" />
        <int name="reqSTR" value="0" />
        <int name="reqDEX" value="0" />
        <int name="reqINT" value="0" />
        <int name="reqLUK" value="0" />
        <int name="cash" value="1" />
    </imgdir>
    <imgdir name="walk1">
        <imgdir name="0">
            <canvas name="cape" width="45" height="81">
                <vector name="origin" x="-18" y="81" />
                <imgdir name="map">
                    <vector name="navel" x="0" y="0" />
                </imgdir>
                <string name="z" value="backWing" />
                <string name="_hash" value="3d448c1caa70da2e62382a178b439fac0f73ee986ab82e10a314330016f05825" />
            </canvas>
        </imgdir>
        <imgdir name="1">
            <canvas name="cape" width="46" height="83">
                <vector name="origin" x="-16" y="80" />
                <imgdir name="map">
                    <vector name="navel" x="0" y="0" />
                </imgdir>
                <string name="z" value="backWing" />
                <string name="_hash" value="365a9782ff3753776e76a3fbcde0eb4dfcd9d5ba7c10f28bc8181432ec809607" />
            </canvas>
        </imgdir>
        <imgdir name="2">
            <canvas name="cape" width="45" height="81">
                <vector name="origin" x="-18" y="81" />
                <imgdir name="map">
                    <vector name="navel" x="0" y="0" />
                </imgdir>
                <string name="z" value="backWing" />
                <string name="_hash" value="ac301e8ba89d45fc42515e480dee59511fb67931b5e83f845642d2d211457279" />
            </canvas>
        </imgdir>
        <imgdir name="3">
            <canvas name="cape" width="44" height="80">
                <vector name="origin" x="-20" y="83" />
                <imgdir name="map">
                    <vector name="navel" x="0" y="0" />
                </imgdir>
                <string name="z" value="backWing" />
                <string name="_hash" value="d361540fe4a3d22b3c98e0bf41bc04214b6be2535bf8fd8008c248ca6770e012" />
            </canvas>
        </imgdir>
    </imgdir>
    <imgdir name="walk2">
        <imgdir name="0">
            <canvas name="cape" width="45" height="81">
                <vector name="origin" x="-13" y="85" />
                <imgdir name="map">
                    <vector name="navel" x="0" y="0" />
                </imgdir>
                <string name="z" value="backWing" />
                <string name="_tobyshield" value="walk1/0/cape" />
            </canvas>
        </imgdir>
        <imgdir name="1">
            <canvas name="cape" width="46" height="83">
                <vector name="origin" x="-11" y="84" />
                <imgdir name="map">
                    <vector name="navel" x="0" y="0" />
                </imgdir>
                <string name="z" value="backWing" />
                <string name="_tobyshield" value="walk1/1/cape" />
            </canvas>
        </imgdir>
        <imgdir name="2">
            <canvas name="cape" width="45" height="81">
                <vector name="origin" x="-13" y="85" />
                <imgdir name="map">
                    <vector name="navel" x="0" y="0" />
                </imgdir>
                <string name="z" value="backWing" />
                <string name="_tobyshield" value="walk1/2/cape" />
            </canvas>
        </imgdir>
        <imgdir name="3">
            <canvas name="cape" width="44" height="80">
                <vector name="origin" x="-15" y="87" />
                <imgdir name="map">
                    <vector name="navel" x="0" y="0" />
                </imgdir>
                <string name="z" value="backWing" />
                <string name="_tobyshield" value="walk1/3/cape" />
            </canvas>
        </imgdir>
    </imgdir>
    <imgdir name="stand1">
        <imgdir name="0">
            <canvas name="cape" width="44" height="80">
                <vector name="origin" x="-18" y="75" />
                <imgdir name="map">
                    <vector name="navel" x="0" y="0" />
                </imgdir>
                <string name="z" value="backWing" />
                <string name="_tobyshield" value="walk1/3/cape" />
            </canvas>
        </imgdir>
        <imgdir name="1">
            <canvas name="cape" width="45" height="81">
                <vector name="origin" x="-18" y="77" />
                <imgdir name="map">
                    <vector name="navel" x="0" y="0" />
                </imgdir>
                <string name="z" value="backWing" />
                <string name="_tobyshield" value="walk1/0/cape" />
            </canvas>
        </imgdir>
        <imgdir name="2">
            <canvas name="cape" width="46" height="83">
                <vector name="origin" x="-18" y="78" />
                <imgdir name="map">
                    <vector name="navel" x="0" y="0" />
                </imgdir>
                <string name="z" value="backWing" />
                <string name="_hash" value="cddd9241fe2259c8e995e24ef9c472b2d7b42bf4b670a03ec55f1e3198fdb172" />
            </canvas>
        </imgdir>
    </imgdir>
    <imgdir name="stand2">
        <imgdir name="0">
            <canvas name="cape" width="44" height="80">
                <vector name="origin" x="-15" y="83" />
                <imgdir name="map">
                    <vector name="navel" x="0" y="0" />
                </imgdir>
                <string name="z" value="backWing" />
                <string name="_tobyshield" value="walk1/3/cape" />
            </canvas>
        </imgdir>
        <imgdir name="1">
            <canvas name="cape" width="45" height="81">
                <vector name="origin" x="-15" y="85" />
                <imgdir name="map">
                    <vector name="navel" x="0" y="0" />
                </imgdir>
                <string name="z" value="backWing" />
                <string name="_tobyshield" value="walk1/0/cape" />
            </canvas>
        </imgdir>
        <imgdir name="2">
            <canvas name="cape" width="46" height="83">
                <vector name="origin" x="-15" y="86" />
                <imgdir name="map">
                    <vector name="navel" x="0" y="0" />
                </imgdir>
                <string name="z" value="backWing" />
                <string name="_tobyshield" value="stand1/2/cape" />
            </canvas>
        </imgdir>
    </imgdir>
    <imgdir name="alert">
        <imgdir name="0">
            <canvas name="cape" width="45" height="83">
                <vector name="origin" x="-13" y="87" />
                <imgdir name="map">
                    <vector name="navel" x="0" y="0" />
                </imgdir>
                <string name="z" value="backWing" />
                <string name="_hash" value="15399cd41c1e2996c8e39d3763b9d178ae56792f567679b12cd23502c93e54d1" />
            </canvas>
        </imgdir>
        <imgdir name="1">
            <canvas name="cape" width="44" height="82">
                <vector name="origin" x="-12" y="85" />
                <imgdir name="map">
                    <vector name="navel" x="0" y="0" />
                </imgdir>
                <string name="z" value="backWing" />
                <string name="_hash" value="5662e8d842f753e143af0056866dc8ac3a30a4a987911520069aa0597af377d3" />
            </canvas>
        </imgdir>
        <imgdir name="2">
            <canvas name="cape" width="42" height="81">
                <vector name="origin" x="-12" y="83" />
                <imgdir name="map">
                    <vector name="navel" x="0" y="0" />
                </imgdir>
                <string name="z" value="backWing" />
                <string name="_hash" value="8ac64f5ba7f2e3b6db29e2d7c08c20063d843b9732bd7ed1eb07e159314b4d47" />
            </canvas>
        </imgdir>
    </imgdir>
    <imgdir name="swingO1">
        <imgdir name="0">
            <canvas name="cape" width="40" height="74">
                <vector name="origin" x="0" y="84" />
                <imgdir name="map">
                    <vector name="navel" x="0" y="0" />
                </imgdir>
                <string name="z" value="capeOverHead" />
                <string name="_hash" value="d49b64b8447c48ab9af12df03eeb84ea83690b62ee16999c4d368d22011c588d" />
            </canvas>
        </imgdir>
        <imgdir name="1">
            <canvas name="cape" width="42" height="82">
                <vector name="origin" x="-15" y="88" />
                <imgdir name="map">
                    <vector name="navel" x="0" y="0" />
                </imgdir>
                <string name="z" value="capeOverHead" />
                <string name="_hash" value="1ae14c197aae66991d28eec1e48129c0a3212d37b5e82ab2a783aed8921d4f46" />
            </canvas>
        </imgdir>
        <imgdir name="2">
            <canvas name="cape" width="65" height="78">
                <vector name="origin" x="-21" y="105" />
                <imgdir name="map">
                    <vector name="navel" x="0" y="0" />
                </imgdir>
                <string name="z" value="backWing" />
                <string name="_hash" value="ae5a9b8011168c9cd61070f7916125797d2be4fb43179056558ba2aa5e8d34fe" />
            </canvas>
        </imgdir>
    </imgdir>
    <imgdir name="swingO2">
        <imgdir name="0">
            <canvas name="cape" width="48" height="78">
                <vector name="origin" x="-8" y="90" />
                <imgdir name="map">
                    <vector name="navel" x="0" y="0" />
                </imgdir>
                <string name="z" value="backWing" />
                <string name="_hash" value="bd0ad1d14c9a7a8a77f2058f777c41610b8f58e8d389d26d3a89ab5e80a9bcff" />
            </canvas>
        </imgdir>
        <imgdir name="1">
            <canvas name="cape" width="62" height="82">
                <vector name="origin" x="3" y="91" />
                <imgdir name="map">
                    <vector name="navel" x="0" y="0" />
                </imgdir>
                <string name="z" value="backWing" />
                <string name="_hash" value="702bdec47440708c3eaa7e6ef0f562ec5ea083d14dabd8dc91bcab37eef0cd0d" />
            </canvas>
        </imgdir>
        <imgdir name="2">
            <canvas name="cape" width="74" height="73">
                <vector name="origin" x="-19" y="79" />
                <imgdir name="map">
                    <vector name="navel" x="0" y="0" />
                </imgdir>
                <string name="z" value="backWing" />
                <string name="_hash" value="0dc1ba3a1ba7b61501879a1d39f453cf05432109e8af3baf6c08d6ec51352cdb" />
            </canvas>
        </imgdir>
    </imgdir>
    <imgdir name="swingO3">
        <imgdir name="0">
            <canvas name="cape" width="45" height="83">
                <vector name="origin" x="-23" y="99" />
                <imgdir name="map">
                    <vector name="navel" x="0" y="0" />
                </imgdir>
                <string name="z" value="backWing" />
                <string name="_hash" value="2933dcaec22ef269ced2d9cf1e7129cfe76ec51a94f7271ce1125519e7afe236" />
            </canvas>
        </imgdir>
        <imgdir name="1">
            <canvas name="cape" width="47" height="87">
                <vector name="origin" x="2" y="88" />
                <imgdir name="map">
                    <vector name="navel" x="0" y="0" />
                </imgdir>
                <string name="z" value="capeOverHead" />
                <string name="_hash" value="923fd56b4c29d87b0e87d2b639f972d66d43052f2823a36d69798e5f0340c2a7" />
            </canvas>
        </imgdir>
        <imgdir name="2">
            <canvas name="cape" width="45" height="87">
                <vector name="origin" x="-12" y="88" />
                <imgdir name="map">
                    <vector name="navel" x="0" y="0" />
                </imgdir>
                <string name="z" value="capeOverHead" />
                <string name="_hash" value="249f74aba38f147e9e3f8d28950c8d81cba61f0618d2d5b5f44f5ed838a44a49" />
            </canvas>
        </imgdir>
    </imgdir>
    <imgdir name="swingOF">
        <imgdir name="0">
            <canvas name="cape" width="42" height="80">
                <vector name="origin" x="-20" y="90" />
                <imgdir name="map">
                    <vector name="navel" x="0" y="0" />
                </imgdir>
                <string name="z" value="backWing" />
                <string name="_hash" value="8b2b7440e94c427b61eb91a2e7cbd994c4deb803f5611e83b47ada2b815f55ba" />
            </canvas>
        </imgdir>
        <imgdir name="1">
            <canvas name="cape" width="58" height="71">
                <vector name="origin" x="63" y="74" />
                <imgdir name="map">
                    <vector name="navel" x="0" y="0" />
                </imgdir>
                <string name="z" value="backCape" />
                <string name="_hash" value="36f85fb92d88dc6e343061a2a4af49d9bda166dcc225824fd7e68b61b0474a06" />
            </canvas>
        </imgdir>
        <imgdir name="2">
            <canvas name="cape" width="42" height="84">
                <vector name="origin" x="7" y="95" />
                <imgdir name="map">
                    <vector name="navel" x="0" y="0" />
                </imgdir>
                <string name="z" value="capeOverHead" />
                <string name="_hash" value="e540e05898cb697a55248c6dd63d9386ef6562d45e32252b1e8703f980c255f1" />
            </canvas>
        </imgdir>
        <imgdir name="3">
            <canvas name="cape" width="83" height="73">
                <vector name="origin" x="-16" y="93" />
                <imgdir name="map">
                    <vector name="navel" x="0" y="0" />
                </imgdir>
                <string name="z" value="backWing" />
                <string name="_hash" value="a183d17ed9e6668e1d762041f3ca00007082f346bfc85e25e00d060436a2cf54" />
            </canvas>
        </imgdir>
    </imgdir>
    <imgdir name="swingT1">
        <imgdir name="0">
            <canvas name="cape" width="67" height="52">
                <vector name="origin" x="-21" y="83" />
                <imgdir name="map">
                    <vector name="navel" x="0" y="0" />
                </imgdir>
                <string name="z" value="backWing" />
                <string name="_hash" value="521f27faddf99fe0082004b888b3407a810e3747337c72bf46debf1c23e5d4fe" />
            </canvas>
        </imgdir>
        <imgdir name="1">
            <canvas name="cape" width="69" height="67">
                <vector name="origin" x="-1" y="95" />
                <imgdir name="map">
                    <vector name="navel" x="0" y="0" />
                </imgdir>
                <string name="z" value="backWing" />
                <string name="_hash" value="b424a4e86f900eecd5913c0ce831940c2dc019edb703f50bec29bb4692391500" />
            </canvas>
        </imgdir>
        <imgdir name="2">
            <canvas name="cape" width="87" height="73">
                <vector name="origin" x="-4" y="76" />
                <imgdir name="map">
                    <vector name="navel" x="0" y="0" />
                </imgdir>
                <string name="z" value="backWing" />
                <string name="_hash" value="84ab9936f239a852c17ffc6163cc9673b98b7c64ea7a4c116eadd9b76f9b6846" />
            </canvas>
        </imgdir>
    </imgdir>
    <imgdir name="swingT2">
        <imgdir name="0">
            <canvas name="cape" width="46" height="85">
                <vector name="origin" x="-16" y="94" />
                <imgdir name="map">
                    <vector name="navel" x="0" y="0" />
                </imgdir>
                <string name="z" value="capeOverHead" />
                <string name="_hash" value="796f57976625dac3917cdb986161d88f16e1a9fd642b463568c1e1b7589b75f8" />
            </canvas>
        </imgdir>
        <imgdir name="1">
            <canvas name="cape" width="50" height="94">
                <vector name="origin" x="34" y="106" />
                <imgdir name="map">
                    <vector name="navel" x="0" y="0" />
                </imgdir>
                <string name="z" value="backWing" />
                <string name="_hash" value="7c15ed769d1d6116ec7446efa90baac4de472b4447d0c3cf15ff36123abf9c30" />
            </canvas>
        </imgdir>
        <imgdir name="2">
            <canvas name="cape" width="46" height="86">
                <vector name="origin" x="-17" y="87" />
                <imgdir name="map">
                    <vector name="navel" x="0" y="0" />
                </imgdir>
                <string name="z" value="backWing" />
                <string name="_hash" value="17585a3dd9a23e5e14b569daaae3f9bf020b47bad9caadfe7f6fc630a932fe06" />
            </canvas>
        </imgdir>
    </imgdir>
    <imgdir name="swingT3">
        <imgdir name="0">
            <canvas name="cape" width="46" height="83">
                <vector name="origin" x="-18" y="85" />
                <imgdir name="map">
                    <vector name="navel" x="0" y="0" />
                </imgdir>
                <string name="z" value="backWing" />
                <string name="_hash" value="c99bab73e0926ecc18e1b17a61568ff9adb219985da4301920890500bac32ee1" />
            </canvas>
        </imgdir>
        <imgdir name="1">
            <canvas name="cape" width="46" height="83">
                <vector name="origin" x="-16" y="83" />
                <imgdir name="map">
                    <vector name="navel" x="0" y="0" />
                </imgdir>
                <string name="z" value="backWing" />
                <string name="_hash" value="1d6dc180448d8d8351c79986114eae3a298c735a7b996e5c5906882348a5ec1b" />
            </canvas>
        </imgdir>
        <imgdir name="2">
            <canvas name="cape" width="83" height="74">
                <vector name="origin" x="5" y="74" />
                <imgdir name="map">
                    <vector name="navel" x="0" y="0" />
                </imgdir>
                <string name="z" value="capeOverHead" />
                <string name="_hash" value="3adbbcee336602cd6660c3da8d52cc58578eea3034cebfd50895802a079b50ea" />
            </canvas>
        </imgdir>
    </imgdir>
    <imgdir name="swingTF">
        <imgdir name="0">
            <canvas name="cape" width="42" height="79">
                <vector name="origin" x="37" y="101" />
                <imgdir name="map">
                    <vector name="navel" x="0" y="0" />
                </imgdir>
                <string name="z" value="capeOverHead" />
                <string name="_hash" value="2d006ff81db469a4fe7ba323fc5c67285d4d7dba53a90b34521a43063210bbca" />
            </canvas>
        </imgdir>
        <imgdir name="1">
            <canvas name="cape" width="40" height="81">
                <vector name="origin" x="-4" y="92" />
                <imgdir name="map">
                    <vector name="navel" x="0" y="0" />
                </imgdir>
                <string name="z" value="backWing" />
                <string name="_hash" value="e9a52647859c410ac184645210683d12f5d5b38f5da60eba4740d4fb56a006d8" />
            </canvas>
        </imgdir>
        <imgdir name="2">
            <canvas name="cape" width="68" height="68">
                <vector name="origin" x="-5" y="92" />
                <imgdir name="map">
                    <vector name="navel" x="0" y="0" />
                </imgdir>
                <string name="z" value="backWing" />
                <string name="_hash" value="2982177eca69be169b90620884354b1c4bb4a88536128ba217e8b4c30a2fd3b0" />
            </canvas>
        </imgdir>
        <imgdir name="3">
            <canvas name="cape" width="90" height="69">
                <vector name="origin" x="0" y="71" />
                <imgdir name="map">
                    <vector name="navel" x="0" y="0" />
                </imgdir>
                <string name="z" value="backWing" />
                <string name="_hash" value="a949a3c1445d7036c7ae2dd5a36cd9261c67819d6e6af8438a3b112e0b4b1195" />
            </canvas>
        </imgdir>
    </imgdir>
    <imgdir name="swingP1">
        <imgdir name="0">
            <canvas name="cape" width="66" height="53">
                <vector name="origin" x="-22" y="85" />
                <imgdir name="map">
                    <vector name="navel" x="0" y="0" />
                </imgdir>
                <string name="z" value="backWing" />
                <string name="_hash" value="66c726eb32865de786c34496c7ff9b3feaf8d007343398fa526b26ad929f9669" />
            </canvas>
        </imgdir>
        <imgdir name="1">
            <canvas name="cape" width="69" height="68">
                <vector name="origin" x="-3" y="97" />
                <imgdir name="map">
                    <vector name="navel" x="0" y="0" />
                </imgdir>
                <string name="z" value="backWing" />
                <string name="_hash" value="dbf0f61c081a78e5deedd31c4e69da62d3448f3d604a1823c1dd80e107f3b761" />
            </canvas>
        </imgdir>
        <imgdir name="2">
            <canvas name="cape" width="88" height="74">
                <vector name="origin" x="-6" y="78" />
                <imgdir name="map">
                    <vector name="navel" x="0" y="0" />
                </imgdir>
                <string name="z" value="backWing" />
                <string name="_hash" value="3d678b3a30e2e515b836a49fc83047e805c363d243916806af0fe54d1624f483" />
            </canvas>
        </imgdir>
    </imgdir>
    <imgdir name="swingP2">
        <imgdir name="0">
            <canvas name="cape" width="46" height="86">
                <vector name="origin" x="-7" y="100" />
                <imgdir name="map">
                    <vector name="navel" x="0" y="0" />
                </imgdir>
                <string name="z" value="capeOverHead" />
                <string name="_hash" value="baad1fc49a9f6fcb1f9985ec6b93dd24be207dff8b285f98808730d41add0621" />
            </canvas>
        </imgdir>
        <imgdir name="1">
            <canvas name="cape" width="52" height="97">
                <vector name="origin" x="13" y="107" />
                <imgdir name="map">
                    <vector name="navel" x="0" y="0" />
                </imgdir>
                <string name="z" value="backWing" />
                <string name="_hash" value="1679ca0dce95b7fbac1c0dfd00e0bfb610402302be243857cf1a95afd21480b5" />
            </canvas>
        </imgdir>
        <imgdir name="2">
            <canvas name="cape" width="45" height="85">
                <vector name="origin" x="-13" y="89" />
                <imgdir name="map">
                    <vector name="navel" x="0" y="0" />
                </imgdir>
                <string name="z" value="backWing" />
                <string name="_hash" value="df5084d0abe69db743ad038ffe4709de8a1a5eee101f609a7bb3a099d1364ddb" />
            </canvas>
        </imgdir>
    </imgdir>
    <imgdir name="swingPF">
        <imgdir name="0">
            <canvas name="cape" width="46" height="84">
                <vector name="origin" x="-28" y="91" />
                <imgdir name="map">
                    <vector name="navel" x="0" y="0" />
                </imgdir>
                <string name="z" value="backWing" />
                <string name="_hash" value="7724e444c92f6b1f0aed6d8f9f7b80ad03d9ec41ca981a23100c96b8b05bfc4a" />
            </canvas>
        </imgdir>
        <imgdir name="1">
            <canvas name="cape" width="49" height="82">
                <vector name="origin" x="-29" y="91" />
                <imgdir name="map">
                    <vector name="navel" x="0" y="0" />
                </imgdir>
                <string name="z" value="backWing" />
                <string name="_hash" value="bfb3f37b8c0b5a49645217b4a15e2f7f58f70161a70f4c0bd4f97c6aee78d75d" />
            </canvas>
        </imgdir>
        <imgdir name="2">
            <canvas name="cape" width="65" height="71">
                <vector name="origin" x="-7" y="103" />
                <imgdir name="map">
                    <vector name="navel" x="0" y="0" />
                </imgdir>
                <string name="z" value="backWing" />
                <string name="_hash" value="7de88e49031cf0cc55b14e2fdaf0d3a6c2f4ce8e7a7385dae27484fab10a2170" />
            </canvas>
        </imgdir>
        <imgdir name="3">
            <canvas name="cape" width="42" height="86">
                <vector name="origin" x="7" y="90" />
                <imgdir name="map">
                    <vector name="navel" x="0" y="0" />
                </imgdir>
                <string name="z" value="capeOverHead" />
                <string name="_hash" value="5b71b4253a4963078cd0918ad89e967bc8efade9e163658f45bdc93b479ca22e" />
            </canvas>
        </imgdir>
    </imgdir>
    <imgdir name="stabO1">
        <imgdir name="0">
            <canvas name="cape" width="58" height="82">
                <vector name="origin" x="-20" y="82" />
                <imgdir name="map">
                    <vector name="navel" x="0" y="0" />
                </imgdir>
                <string name="z" value="backWing" />
                <string name="_hash" value="053c74fce9ad26de431978dc6e499b0ac3c3b0a92adc07f0a3478271614bd1ec" />
            </canvas>
        </imgdir>
        <imgdir name="1">
            <canvas name="cape" width="69" height="77">
                <vector name="origin" x="-16" y="80" />
                <imgdir name="map">
                    <vector name="navel" x="0" y="0" />
                </imgdir>
                <string name="z" value="capeOverHead" />
                <string name="_hash" value="34ed017f13190da8e32afd2c21bb2befd2f43d906aeea96b5807251869151268" />
            </canvas>
        </imgdir>
    </imgdir>
    <imgdir name="stabO2">
        <imgdir name="0">
            <canvas name="cape" width="58" height="83">
                <vector name="origin" x="-19" y="86" />
                <imgdir name="map">
                    <vector name="navel" x="0" y="0" />
                </imgdir>
                <string name="z" value="backWing" />
                <string name="_hash" value="8dd3cc5e17ba94bf2d813c3cb585852e02e3c5b71103b68559b2c2d6c5f6a9bf" />
            </canvas>
        </imgdir>
        <imgdir name="1">
            <canvas name="cape" width="69" height="77">
                <vector name="origin" x="-9" y="79" />
                <imgdir name="map">
                    <vector name="navel" x="0" y="0" />
                </imgdir>
                <string name="z" value="capeOverHead" />
                <string name="_tobyshield" value="stabO1/1/cape" />
            </canvas>
        </imgdir>
    </imgdir>
    <imgdir name="stabOF">
        <imgdir name="0">
            <canvas name="cape" width="46" height="84">
                <vector name="origin" x="-15" y="89" />
                <imgdir name="map">
                    <vector name="navel" x="0" y="0" />
                </imgdir>
                <string name="z" value="backWing" />
                <string name="_hash" value="3d712e78085182951337d7b6d37f24053347de26a007a044144a76ed01cacafc" />
            </canvas>
        </imgdir>
        <imgdir name="1">
            <canvas name="cape" width="51" height="80">
                <vector name="origin" x="-20" y="81" />
                <imgdir name="map">
                    <vector name="navel" x="0" y="0" />
                </imgdir>
                <string name="z" value="backWing" />
                <string name="_hash" value="e252ff50015b9c731f1efe1680ec60626107b4f6dd4a7f97be28c3253e1adf71" />
            </canvas>
        </imgdir>
        <imgdir name="2">
            <canvas name="cape" width="65" height="65">
                <vector name="origin" x="2" y="66" />
                <imgdir name="map">
                    <vector name="navel" x="0" y="0" />
                </imgdir>
                <string name="z" value="backWing" />
                <string name="_hash" value="53c9ae0b01f9ec24dfa3743fdb16ed31e252922464b4adac5e51e0b11e4d4721" />
            </canvas>
        </imgdir>
    </imgdir>
    <imgdir name="stabT1">
        <imgdir name="0">
            <canvas name="cape" width="47" height="83">
                <vector name="origin" x="-24" y="91" />
                <imgdir name="map">
                    <vector name="navel" x="0" y="0" />
                </imgdir>
                <string name="z" value="backWing" />
                <string name="_hash" value="99d6e80717330da2c059471d96c81a57f828cd7e96231cfb8e2eb2168c1a62e3" />
            </canvas>
        </imgdir>
        <imgdir name="1">
            <canvas name="cape" width="48" height="84">
                <vector name="origin" x="-26" y="89" />
                <imgdir name="map">
                    <vector name="navel" x="0" y="0" />
                </imgdir>
                <string name="z" value="backWing" />
                <string name="_hash" value="5251361c6c8597786c4e6a6d80dbd10d8abba94e5690a73cfa7fbb4a0f53c183" />
            </canvas>
        </imgdir>
        <imgdir name="2">
            <canvas name="cape" width="79" height="68">
                <vector name="origin" x="-14" y="72" />
                <imgdir name="map">
                    <vector name="navel" x="0" y="0" />
                </imgdir>
                <string name="z" value="backWing" />
                <string name="_hash" value="09e9f9fba3dde9a863a328ff7a76721a588b4f5114764287130d03cfd07656a4" />
            </canvas>
        </imgdir>
    </imgdir>
    <imgdir name="stabT2">
        <imgdir name="0">
            <canvas name="cape" width="45" height="85">
                <vector name="origin" x="-20" y="92" />
                <imgdir name="map">
                    <vector name="navel" x="0" y="0" />
                </imgdir>
                <string name="z" value="backWing" />
                <string name="_hash" value="c6e6978ce49d17f53d9f8160e8445b951e8a2e360c8e11c373d516204356843f" />
            </canvas>
        </imgdir>
        <imgdir name="1">
            <canvas name="cape" width="48" height="85">
                <vector name="origin" x="-19" y="90" />
                <imgdir name="map">
                    <vector name="navel" x="0" y="0" />
                </imgdir>
                <string name="z" value="backWing" />
                <string name="_hash" value="5a8333481421a0efaa33ea412f34e08634ff009875aad895e1396b52af7b0110" />
            </canvas>
        </imgdir>
        <imgdir name="2">
            <canvas name="cape" width="79" height="68">
                <vector name="origin" x="-8" y="66" />
                <imgdir name="map">
                    <vector name="navel" x="0" y="0" />
                </imgdir>
                <string name="z" value="backWing" />
                <string name="_tobyshield" value="stabT1/2/cape" />
            </canvas>
        </imgdir>
    </imgdir>
    <imgdir name="stabTF">
        <imgdir name="0">
            <uol name="cape" value="../../swingPF/0/cape" />
        </imgdir>
        <imgdir name="1">
            <uol name="cape" value="../../swingPF/1/cape" />
        </imgdir>
        <imgdir name="2">
            <canvas name="cape" width="58" height="85">
                <vector name="origin" x="-13" y="91" />
                <imgdir name="map">
                    <vector name="navel" x="0" y="0" />
                </imgdir>
                <string name="z" value="backWing" />
                <string name="_hash" value="41a65d0c5033bb23357186d2953b76aff830e9cc8c72a545f9cc60650ccf83d8" />
            </canvas>
        </imgdir>
        <imgdir name="3">
            <canvas name="cape" width="72" height="101">
                <vector name="origin" x="-10" y="101" />
                <imgdir name="map">
                    <vector name="navel" x="0" y="0" />
                </imgdir>
                <string name="z" value="backWing" />
                <string name="_hash" value="cea3494dddc4f4ebf13d9f88d4c1553f80a8641eb0606ece93337057a3c6b053" />
            </canvas>
        </imgdir>
    </imgdir>
    <imgdir name="shoot1">
        <imgdir name="0">
            <canvas name="cape" width="45" height="81">
                <vector name="origin" x="-12" y="91" />
                <imgdir name="map">
                    <vector name="navel" x="0" y="0" />
                </imgdir>
                <string name="z" value="backWing" />
                <string name="_hash" value="8eb5fcad4f9ced30f549d82db3065a54b34c591dfd5a0a45d5bbfc27e8cd7d9e" />
            </canvas>
        </imgdir>
        <imgdir name="1">
            <canvas name="cape" width="42" height="79">
                <vector name="origin" x="-15" y="92" />
                <imgdir name="map">
                    <vector name="navel" x="0" y="0" />
                </imgdir>
                <string name="z" value="backWing" />
                <string name="_hash" value="ab1d339b43f872b1347c3d06d64b1ec061c961d46f570338b9325efdc45bad57" />
            </canvas>
        </imgdir>
        <imgdir name="2">
            <uol name="cape" value="../1/cape" />
        </imgdir>
    </imgdir>
    <imgdir name="shoot2">
        <imgdir name="0">
            <canvas name="cape" width="47" height="80">
                <vector name="origin" x="-15" y="91" />
                <imgdir name="map">
                    <vector name="navel" x="0" y="0" />
                </imgdir>
                <string name="z" value="backWing" />
                <string name="_hash" value="195ea18eed29149d1d0dfbdd39fed87b7de6ac25e9b7a3626ee148ebb848c8b5" />
            </canvas>
        </imgdir>
        <imgdir name="1">
            <canvas name="cape" width="47" height="83">
                <vector name="origin" x="-15" y="94" />
                <imgdir name="map">
                    <vector name="navel" x="0" y="0" />
                </imgdir>
                <string name="z" value="backWing" />
                <string name="_hash" value="44ff980486f1f4d9908963dcc0a6da04784fdf7931a15e1e2bc843bf717032e1" />
            </canvas>
        </imgdir>
        <imgdir name="2">
            <uol name="cape" value="../0/cape" />
        </imgdir>
        <imgdir name="3">
            <uol name="cape" value="../0/cape" />
        </imgdir>
        <imgdir name="4">
            <canvas name="cape" width="46" height="80">
                <vector name="origin" x="-15" y="91" />
                <imgdir name="map">
                    <vector name="navel" x="0" y="0" />
                </imgdir>
                <string name="z" value="backWing" />
                <string name="_hash" value="2d1a3c9b12687ce6bd8b37f6d06df9b231de270a3bc4c149c8ee4931e8a7ed25" />
            </canvas>
        </imgdir>
    </imgdir>
    <imgdir name="shootF">
        <imgdir name="0">
            <canvas name="cape" width="42" height="79">
                <vector name="origin" x="-12" y="90" />
                <imgdir name="map">
                    <vector name="navel" x="0" y="0" />
                </imgdir>
                <string name="z" value="backWing" />
                <string name="_tobyshield" value="shoot1/1/cape" />
            </canvas>
        </imgdir>
        <imgdir name="1">
            <canvas name="cape" width="42" height="82">
                <vector name="origin" x="-15" y="93" />
                <imgdir name="map">
                    <vector name="navel" x="0" y="0" />
                </imgdir>
                <string name="z" value="backWing" />
                <string name="_hash" value="3432990ec6358cb72a4ccf05380675e4a88bdb70f5f560420cfc6c60cecfc61a" />
            </canvas>
        </imgdir>
        <imgdir name="2">
            <uol name="cape" value="../1/cape" />
        </imgdir>
    </imgdir>
    <imgdir name="proneStab">
        <imgdir name="0">
            <canvas name="cape" width="58" height="84">
                <vector name="origin" x="-6" y="88" />
                <imgdir name="map">
                    <vector name="navel" x="0" y="0" />
                </imgdir>
                <string name="z" value="cape" />
                <string name="_hash" value="b6203707a7d33ba21789d2348c0d011ff8c821f9b50824c4b721301dcef0fedd" />
            </canvas>
        </imgdir>
        <imgdir name="1">
            <canvas name="cape" width="66" height="78">
                <vector name="origin" x="-4" y="82" />
                <imgdir name="map">
                    <vector name="navel" x="0" y="0" />
                </imgdir>
                <string name="z" value="cape" />
                <string name="_hash" value="1589bb91ca9b9a8e785e1a7364e4d1086c8d071d0aa137aee090c3eb7da79e89" />
            </canvas>
        </imgdir>
    </imgdir>
    <imgdir name="prone">
        <imgdir name="0">
            <uol name="cape" value="../../proneStab/0/cape" />
        </imgdir>
    </imgdir>
    <imgdir name="heal">
        <imgdir name="0">
            <uol name="cape" value="../../alert/1/cape" />
        </imgdir>
        <imgdir name="1">
            <uol name="cape" value="../../swingO2/1/cape" />
        </imgdir>
        <imgdir name="2">
            <uol name="cape" value="../../swingO2/0/cape" />
        </imgdir>
    </imgdir>
    <imgdir name="fly">
        <imgdir name="0">
            <canvas name="cape" width="45" height="81">
                <vector name="origin" x="-14" y="92" />
                <imgdir name="map">
                    <vector name="navel" x="0" y="0" />
                </imgdir>
                <string name="z" value="backWing" />
                <string name="_hash" value="1bb080eb16880dacc5d6dcea7b0d5c631b3ddb10b5660b399b0e37af5ffc3672" />
            </canvas>
        </imgdir>
        <imgdir name="1">
            <canvas name="cape" width="46" height="84">
                <vector name="origin" x="-14" y="95" />
                <imgdir name="map">
                    <vector name="navel" x="0" y="0" />
                </imgdir>
                <string name="z" value="backWing" />
                <string name="_hash" value="cf428ee983134b91e6bea30b2c0994b8f70f47579ba88f0fd867536ce6658b21" />
            </canvas>
        </imgdir>
    </imgdir>
    <imgdir name="jump">
        <imgdir name="0">
            <canvas name="cape" width="49" height="91">
                <vector name="origin" x="-16" y="99" />
                <imgdir name="map">
                    <vector name="navel" x="0" y="0" />
                </imgdir>
                <string name="z" value="backWing" />
                <string name="_hash" value="d8b76bc6531deff37fae9295b8e3a355057fe8f0fda165dedbfc137c8520d290" />
            </canvas>
        </imgdir>
    </imgdir>
    <imgdir name="sit">
        <imgdir name="0">
            <canvas name="cape" width="46" height="84">
                <vector name="origin" x="-11" y="83" />
                <imgdir name="map">
                    <vector name="navel" x="0" y="0" />
                </imgdir>
                <string name="z" value="backWing" />
                <string name="_hash" value="2045261dbe6e9d8cff3b65efc983d9403cabdd63b1ca16b0a52db3d02e3aa252" />
            </canvas>
        </imgdir>
    </imgdir>
    <imgdir name="ladder">
        <imgdir name="0">
            <canvas name="cape" width="47" height="84">
                <vector name="origin" x="-11" y="87" />
                <imgdir name="map">
                    <vector name="navel" x="0" y="0" />
                </imgdir>
                <string name="z" value="weaponOverGlove" />
                <string name="_hash" value="9e9bcc2a65c052f3494359bafb995196bc09ebda98b447a1cfd2a556ac347ccf" />
            </canvas>
        </imgdir>
        <imgdir name="1">
            <canvas name="cape" width="46" height="85">
                <vector name="origin" x="-12" y="88" />
                <imgdir name="map">
                    <vector name="navel" x="0" y="0" />
                </imgdir>
                <string name="z" value="weaponOverGlove" />
                <string name="_hash" value="47825f57c853d0364af6cf18a343b877fb25f9ed667b6c1a7eadbb22d8a1d807" />
            </canvas>
        </imgdir>
    </imgdir>
    <imgdir name="rope">
        <imgdir name="0">
            <canvas name="cape" width="46" height="84">
                <vector name="origin" x="-10" y="84" />
                <imgdir name="map">
                    <vector name="navel" x="0" y="0" />
                </imgdir>
                <string name="z" value="weaponOverGlove" />
                <string name="_hash" value="52666689c84cedd481a7819dc3a0815ae3713261c512f430209d738b69f2e63c" />
            </canvas>
        </imgdir>
        <imgdir name="1">
            <canvas name="cape" width="46" height="86">
                <vector name="origin" x="-11" y="92" />
                <imgdir name="map">
                    <vector name="navel" x="0" y="0" />
                </imgdir>
                <string name="z" value="weaponOverGlove" />
                <string name="_hash" value="adf78ec87383083f88521ee08987414b381c5e740c29eb475032bae37dfeff0c" />
            </canvas>
        </imgdir>
    </imgdir>
</imgdir>